{
  "@context": [
    "https://www.w3.org/2018/credentials/v1",
    "https://w3id.org/vaccination/v1"
  ],
  "type": [
    "VerifiableCredential",
    "VaccinationCertificate"
  ],
  "id": "urn:uvci:MzY2YjQ1MGUtNjczNC00YzA3LWI0ZjUtN2U4YzVkOTlhYWU0",
  "name": "Measles",
  "description": "Measles",
  "credentialSubject": {
    "type": "VaccinationEvent",
    "batchNumber": "843",
    "administeringCentre": "U.S. Public Health Authority",
    "healthProfessional": "U.S. Public Health Authority",
    "countryOfVaccination": "United States of America",
    "recipient": {
      "type": "VaccineRecipient",
      "givenName": "JOHN",
      "familyName": "SMITH",
      "gender": "Male",
      "birthDate": "1958-07-17"
    },
    "vaccine": {
      "type": "Vaccine",
      "disease": "Measles",
      "atcCode": "XM28X5"
    }
  }
}